{
  "build": {
    "content": [
      {
        "files": [
          "**/*.md",
          "**/*.yml"
        ],
        "exclude": [
          "**/obj/**",
          "**/includes/**",
          "_themes/**",
          "_themes.pdf/**",
          "README.md",
          "LICENSE",
          "LICENSE-CODE",
          "ThirdPartyNotices"
        ]
      }
    ],
    "resource": [
      {
        "files": [
          "**/*.png",
          "**/*.jpg"
        ],
        "exclude": [
          "**/obj/**",
          "**/includes/**",
          "_themes/**",
          "_themes.pdf/**"
        ]
      }
    ],
    "overwrite": [],
    "externalReference": [],
    "globalMetadata": {
      "ROBOTS": "INDEX, FOLLOW",
      "searchScope": ["OpenSpecs"],
      "uhfHeaderId": "MSDocsHeader-OpenSpecs",
      "ms.prod": "openspecs-office",
      "topic": "conceptual",
      "contributors_to_exclude": ["mrsgit09","skesseks","jmazzotta","andrewdavidoff","Incyuna2z","enoch717","donnyluu","cindysomer","erikadoyle","champagnie","stguty","jasonfis-msft","Hoffman2407","wcblue","AlfredHellstern"],
      "ms.topic": "conceptual",
      "_comment_feedback_system": "GitHub",
      "_comment_feedback_github_repo": "MicrosoftDocs/open_specs_blog",
      "protocol_rendering": true,
      "ms.author": "cindyle",
      "author": "cindysomer"
      },
    "fileMetadata": {},
    "template": [],
    "dest": "open_specs_blog",
    "markdownEngineName": "markdig"
  }
}